uvforge/__init__.py
uvforge/main.py
uvforge/scaffolder.py
uvforge/templates.py
uvforge-0.1.1.dist-info/licenses/LICENSE
uvforge-0.1.1.dist-info/METADATA
uvforge-0.1.1.dist-info/WHEEL
uvforge-0.1.1.dist-info/entry_points.txt
uvforge-0.1.1.dist-info/top_level.txt
uvforge-0.1.1.dist-info/RECORD
