Metadata-Version: 2.4
Name: uvforge
Version: 0.1.1
Summary: A CLI tool to scaffold Python projects with uv
Author-email: Manuel Rodríguez Sutil <mrodsut@gmail.com>
License: MIT License
Project-URL: Homepage, https://github.com/manursutil/py-template
Project-URL: Repository, https://github.com/manursutil/py-template
Project-URL: Issues, https://github.com/manursutil/py-template/issues
Keywords: cli,template,scaffold,python,uv
Classifier: Development Status :: 4 - Beta
Classifier: Environment :: Console
Classifier: Intended Audience :: Developers
Classifier: License :: OSI Approved :: MIT License
Classifier: Operating System :: OS Independent
Classifier: Programming Language :: Python :: 3
Classifier: Programming Language :: Python :: 3.13
Classifier: Topic :: Software Development :: Libraries :: Python Modules
Classifier: Topic :: Software Development :: Code Generators
Requires-Python: >=3.13
License-File: LICENSE
Requires-Dist: click>=8.2.1
Requires-Dist: inquirerpy>=0.3.4
Requires-Dist: pyfiglet>=1.0.4
Requires-Dist: rich>=14.1.0
Dynamic: license-file
